octokit_routes/__init__.py
octokit_routes/routes/api.github.com.json
octokit_routes/routes/ghe-2.18.json
octokit_routes/routes/ghe-2.19.json
octokit_routes/routes/ghe-2.20.json
octokit_routes/routes/ghe-2.21.json
octokit_routes/webhooks/index.json
octokitpy_routes-2.5.0.dist-info/LICENSE
octokitpy_routes-2.5.0.dist-info/METADATA
octokitpy_routes-2.5.0.dist-info/WHEEL
octokitpy_routes-2.5.0.dist-info/top_level.txt
octokitpy_routes-2.5.0.dist-info/RECORD
